[
    {
        "title": "TWS F9 Bluetooth Earphone Touch Wireless Headphones 8D Stereo Sports Earbuds\u00a0EEP-582910",
        "url": "https://www.tinydeal.com/tws-f9-bluetooth-earphone-touch-wireless-headphones-8d-stereo-sports-earbuds-p-200780.html",
        "discounted_price": "$12.07",
        "original_price": "$24.02 "
    },
    {
        "title": "Transparent Anti Droplet Dust-proof Medical Face Shield Face Cover Mask\u00a0HHI-581539",
        "url": "https://www.tinydeal.com/transparent-anti-droplet-dust-proof-medical-face-shield-face-cover-mask-p-200336.html",
        "discounted_price": "$2.82",
        "original_price": "$3.48 "
    },
    {
        "title": "Fsat Quick Charge 3.0 4.0 QC3.0 Fast Charging Tablet Wall Adapter\u00a0HHITH-582324",
        "url": "https://www.tinydeal.com/fsat-quick-charge-30-40-qc30-fast-charging-tablet-wall-adapter-p-201049.html",
        "discounted_price": "$3.75",
        "original_price": "$6.74 "
    },
    {
        "title": "10 x Transparent Anti Droplet Dust-proof Medical Face Shield Face Cover Mask\u00a0KB-581546",
        "url": "https://www.tinydeal.com/10-x-transparent-anti-droplet-dust-proof-medical-face-shield-face-cover-mask-p-200338.html",
        "discounted_price": "$13.83",
        "original_price": "$24.61 "
    },
    {
        "title": "Micro SD TF Card 32GB Class Flash Memory Card for Smartphone Adapter\u00a0EFM-582223",
        "url": "https://www.tinydeal.com/micro-sd-tf-card-32gb-class-flash-memory-card-for-smartphone-adapter-p-201054.html",
        "discounted_price": "$4.77",
        "original_price": "$8.59 "
    },
    {
        "title": "Mini Airtight Sealer Machine for Plastic Bag - Assorted Color\u00a0HLI-48626",
        "url": "https://www.tinydeal.com/mini-airtight-sealer-machine-for-plastic-bag-assorted-color-p-39392.html",
        "discounted_price": "$2.52",
        "original_price": "$5.86 "
    },
    {
        "title": "100 LED Solar Light  Solar Lamp Powered Sunlight 3 Modes PIR Motion Sensor\u00a0RTH-577401",
        "url": "https://www.tinydeal.com/100-led-solar-light-solar-lamp-powered-sunlight-3-modes-pir-motion-sensor-p-201640.html",
        "discounted_price": "$9.02",
        "original_price": "$14.89 "
    },
    {
        "title": "Wireless Headphones Bluetooth 5.0 Foldable Stereo Adjustable Earphones\u00a0RTH-578691",
        "url": "https://www.tinydeal.com/wireless-headphones-bluetooth-50-foldable-stereo-adjustable-earphones-p-201646.html",
        "discounted_price": "$15.00",
        "original_price": "$21.75 "
    },
    {
        "title": "0.25W Intelligent Cabinet Sensor Lights\u00a0HHI-546845",
        "url": "https://www.tinydeal.com/025w-intelligent-cabinet-sensor-lights-p-174242.html",
        "discounted_price": "$1.96",
        "original_price": "$5.28 "
    },
    {
        "title": "Fully USB Charging Automatic Foam Soap Dispenser Deep Cleaning\u00a0HHI-581206",
        "url": "https://www.tinydeal.com/fully-usb-charging-automatic-foam-soap-dispenser-deep-cleaning-p-201087.html",
        "discounted_price": "$19.11",
        "original_price": "$22.93 "
    },
    {
        "title": "X96Q Android 10.0 TV Box Quad Core Allwinner H313 4K TV Box 2GB RAM 16GB ROM\u00a0E-581778",
        "url": "https://www.tinydeal.com/x96q-android-100-tv-box-quad-core-allwinner-h313-4k-tv-box-2gb-ram-16gb-rom-p-201107.html",
        "discounted_price": "$31.15",
        "original_price": "$43.61 "
    },
    {
        "title": "Air Circulation Fan Mute Desktop Fans Atmosphere Ventilation Electric Fan\u00a0HHI-581327",
        "url": "https://www.tinydeal.com/air-circulation-fan-mute-desktop-fans-atmosphere-ventilation-electric-fan-p-200717.html",
        "discounted_price": "$19.21",
        "original_price": "$34.58 "
    },
    {
        "title": "Silicone Nipple Cover Stickers Adhesive Bra Reusable Invisible Nipple Cover\u00a0HHI-550767",
        "url": "https://www.tinydeal.com/silicone-nipple-cover-stickers-adhesive-bra-reusable-invisible-nipple-cover-p-175493.html",
        "discounted_price": "$2.00",
        "original_price": "$2.40 "
    },
    {
        "title": "Autumn Winter Leather Baseball Cap Men Women Gorras Planas Snapback Hat\u00a0RTH-576721",
        "url": "https://www.tinydeal.com/autumn-winter-leather-baseball-cap-men-women-gorras-planas-snapback-hat-p-201587.html",
        "discounted_price": "$8.54",
        "original_price": "$10.67 "
    },
    {
        "title": "Wireless Earphones TWS Wireless Bluetooth 5.0 LED Display Waterproof Headphone\u00a0EEP-580809",
        "url": "https://www.tinydeal.com/wireless-earphones-tws-wireless-bluetooth-50-led-display-waterproof-headphone-p-201417.html",
        "discounted_price": "$16.00",
        "original_price": "$17.59 "
    },
    {
        "title": "3 in 1 Cable Nylon-Coating Fast Charging 8Pin Type-C Micro-USB\u00a0EPA-530685",
        "url": "https://www.tinydeal.com/3-in-1-cable-nylon-coating-fast-charging-8pin-type-micro-usb-p-165980.html",
        "discounted_price": "$2.53",
        "original_price": "$4.37 "
    },
    {
        "title": "Xiaomi Turok Steinhardt TS Brand Polarized Stainless Mirror Lenses Sunglasses\u00a0S-582106",
        "url": "https://www.tinydeal.com/xiaomi-turok-steinhardt-ts-brand-polarized-stainless-mirror-lenses-sunglasses-p-200936.html",
        "discounted_price": "$20.22",
        "original_price": "$34.38 "
    },
    {
        "title": "K08 Wireless Headphone Bluetooth5.0 Bone Conduction Headsets Wireless\u00a0EEP-583532",
        "url": "https://www.tinydeal.com/k08-wireless-headphone-bluetooth50-bone-conduction-headsets-wireless-p-201440.html",
        "discounted_price": "$12.33",
        "original_price": "$22.81 "
    },
    {
        "title": "Compression Socks for Man Woman\u00a0STH-563907",
        "url": "https://www.tinydeal.com/compression-socks-for-man-woman-p-180225.html",
        "discounted_price": "$2.43",
        "original_price": "$6.45 "
    },
    {
        "title": "GM320 Infrared Thermometer Non-Contact Laser Gun IR Thermometer\u00a0EDT-528767",
        "url": "https://www.tinydeal.com/gm320-infrared-thermometer-non-contact-laser-gun-ir-thermometer-p-165306.html",
        "discounted_price": "$16.97",
        "original_price": "$18.94 "
    },
    {
        "title": "F9 TWS Wireless Earphones Bluetooth 5.0 F9 TWS Bluetooth headphone\u00a0EEP-583405",
        "url": "https://www.tinydeal.com/f9-tws-wireless-earphones-bluetooth-50-f9-tws-bluetooth-headphone-p-201446.html",
        "discounted_price": "$12.13",
        "original_price": "$21.84 "
    },
    {
        "title": "Genuine Leather Man Messenger Bags Vintage Cow Leather Small Shoulder Bag\u00a0DBA-584138",
        "url": "https://www.tinydeal.com/genuine-leather-man-messenger-bags-vintage-cow-leather-small-shoulder-bag-p-202214.html",
        "discounted_price": "$24.87",
        "original_price": "$44.76 "
    },
    {
        "title": "Kangaroo Brand Leather Messenger Bag Man Handbag Chest Bag\u00a0RTH-577738",
        "url": "https://www.tinydeal.com/kangaroo-brand-leather-messenger-bag-man-handbag-chest-bag-p-200744.html",
        "discounted_price": "$17.82",
        "original_price": "$21.38 "
    },
    {
        "title": "100LED Solar Light Outdoor Solar Lamp PIR Motion Sensor Wall Light Waterproof\u00a0HHIHE-582872",
        "url": "https://www.tinydeal.com/100led-solar-light-outdoor-solar-lamp-pir-motion-sensor-wall-light-waterproof-p-201245.html",
        "discounted_price": "$7.49",
        "original_price": "$10.12 "
    },
    {
        "title": "70mai Smart Dash Cam Pro English Voice Car DVR Camera GPS Auto Night Vision\u00a0RCM-581275",
        "url": "https://www.tinydeal.com/70mai-smart-dash-cam-pro-english-voice-car-dvr-camera-gps-auto-night-vision-p-201053.html",
        "discounted_price": "$90.09",
        "original_price": "$108.11 "
    },
    {
        "title": "Outdoor Lights Solar Powered LED Wall Lamp Porch Lights Sensor Motion Sensor\u00a0HSI-582757",
        "url": "https://www.tinydeal.com/outdoor-lights-solar-powered-led-wall-lamp-porch-lights-sensor-motion-sensor-p-201016.html",
        "discounted_price": "$8.17",
        "original_price": "$14.70 "
    },
    {
        "title": "Smart Wireless Bluetooth Stereo Headset Headphone with MIC\u00a0RTH-576453",
        "url": "https://www.tinydeal.com/smart-wireless-bluetooth-stereo-headset-headphone-with-mic-p-201645.html",
        "discounted_price": "$15.69",
        "original_price": "$25.11 "
    },
    {
        "title": "Silicone Stretch Lids Food Saver Covers Set \u2013 6pcs\u00a0HKI-550666",
        "url": "https://www.tinydeal.com/silicone-stretch-lids-food-saver-covers-set-\u2013-6pcs-p-175450.html",
        "discounted_price": "$5.28",
        "original_price": "$6.87 "
    },
    {
        "title": "Men Genuine Leather Strap Male Belts for New Classic Vintage Pin Buckle Strap\u00a0HHI-578703",
        "url": "https://www.tinydeal.com/men-genuine-leather-strap-male-belts-for-new-classic-vintage-pin-buckle-strap-p-201601.html",
        "discounted_price": "$8.18",
        "original_price": "$15.13 "
    },
    {
        "title": "Personal Portable Photography Studio LED Light Room Light Weight\u00a0EVA-538137",
        "url": "https://www.tinydeal.com/personal-portable-photography-studio-led-light-room-light-weight-p-170497.html",
        "discounted_price": "$10.62",
        "original_price": "$18.48 "
    },
    {
        "title": "DUBERY Polarized Sunglasses Men's Driving Shades Male Sun Glasses\u00a0S-580864",
        "url": "https://www.tinydeal.com/dubery-polarized-sunglasses-mens-driving-shades-male-sun-glasses-p-200630.html",
        "discounted_price": "$5.89",
        "original_price": "$15.20 "
    },
    {
        "title": "E1 Bone Conduction Headphones Bluetooth 4.1 Wireless Bass HiFi Headsets\u00a0EEP-545247",
        "url": "https://www.tinydeal.com/e1-bone-conduction-headphones-bluetooth-41-wireless-bass-hifi-headsets-p-173784.html",
        "discounted_price": "$11.12",
        "original_price": "$74.68 "
    },
    {
        "title": "DUBERY Vintage Sunglasses Polarized Men's Sun Glasses For Men\u00a0S-580871",
        "url": "https://www.tinydeal.com/dubery-vintage-sunglasses-polarized-mens-sun-glasses-for-men-p-200631.html",
        "discounted_price": "$6.32",
        "original_price": "$8.22 "
    },
    {
        "title": "GM321 Non-contact Infrared Thermometer -50\u00b0 to 380\u00b0\u00a0EDT-568819",
        "url": "https://www.tinydeal.com/gm321-non-contact-infrared-thermometer-50\u00b0-to-380\u00b0-p-181807.html",
        "discounted_price": "$24.87",
        "original_price": "$29.84 "
    },
    {
        "title": "Xiaomi ENCHEN Sharp3S Men's Electric Hair Clipper USB Rechargeable Hair Trimmer\u00a0HHIHE-581692",
        "url": "https://www.tinydeal.com/xiaomi-enchen-sharp3s-mens-electric-hair-clipper-usb-rechargeable-hair-trimmer-p-201119.html",
        "discounted_price": "$18.40",
        "original_price": "$27.59 "
    },
    {
        "title": "Xiaomi 3D Men Electric Shaver Razor Enchen BlackStone3 IPX7 Waterproof\u00a0HHI-580937",
        "url": "https://www.tinydeal.com/xiaomi-3d-men-electric-shaver-razor-enchen-blackstone3-ipx7-waterproof-p-200797.html",
        "discounted_price": "$24.27",
        "original_price": "$29.13 "
    },
    {
        "title": "XIAOMI MIJIA VIOMI Blender Electric Kitchen Mixer Juicer Fruit Cup Quick Juicing\u00a0HHI-581813",
        "url": "https://www.tinydeal.com/xiaomi-mijia-viomi-blender-electric-kitchen-mixer-juicer-fruit-cup-quick-juicing-p-201105.html",
        "discounted_price": "$33.74",
        "original_price": "$40.49 "
    },
    {
        "title": "S03 Smart Watch Waterproof Activity Tracker Smart Band Bracelet\u00a0E-582866",
        "url": "https://www.tinydeal.com/s03-smart-watch-waterproof-activity-tracker-smart-band-bracelet-p-200781.html",
        "discounted_price": "$11.95",
        "original_price": "$24.02 "
    },
    {
        "title": "2PCS Automobile Electrostatic Sunshade Car Sunscreen Sticker\u00a0RTH-391611",
        "url": "https://www.tinydeal.com/2pcs-automobile-electrostatic-sunshade-car-sunscreen-sticker--p-148929.html",
        "discounted_price": "$4.23",
        "original_price": "$7.79 "
    },
    {
        "title": "1/2/4 Pair Magnetic Therapy Thermal Self-Heating Knee Pad Belt\u00a0BBI-276865",
        "url": "https://www.tinydeal.com/124-pair-magnetic-therapy-thermal-self-heating-knee-pad-belt-p-118227.html",
        "discounted_price": "$3.64",
        "original_price": "$4.74 "
    },
    {
        "title": "M108 Smart Wireless WiFi HD Visual Doorbell IP Door Bell Infrared Night Vision\u00a0HHIHE-580663",
        "url": "https://www.tinydeal.com/m108-smart-wireless-wifi-hd-visual-doorbell-ip-door-bell-infrared-night-vision--p-201397.html",
        "discounted_price": "$37.58",
        "original_price": "$60.12 "
    },
    {
        "title": "Camping Sleeping Pad Ultralight Waterproof self Inflating Sleeping Hiking\u00a0HHI-582472",
        "url": "https://www.tinydeal.com/camping-sleeping-pad-ultralight-waterproof-self-inflating-sleeping-hiking-p-200843.html",
        "discounted_price": "$30.96",
        "original_price": "$40.25 "
    },
    {
        "title": "Men Electric Shaver Razor Beard Hair Clipper Trimmer Grooming Rechargeable Hair\u00a0HHI-580827",
        "url": "https://www.tinydeal.com/men-electric-shaver-razor-beard-hair-clipper-trimmer-grooming-rechargeable-hair-p-201462.html",
        "discounted_price": "$24.27",
        "original_price": "$35.19 "
    },
    {
        "title": "Outdoor USB Rechargeable Personal Alarm Emergency Security Alarm Keychain\u00a0S-583319",
        "url": "https://www.tinydeal.com/outdoor-usb-rechargeable-personal-alarm-emergency-security-alarm-keychain-p-200941.html",
        "discounted_price": "$5.93",
        "original_price": "$8.89 "
    },
    {
        "title": "Liquid Luminous Coating Fluorescent Body/Face Paint Luminous Acrylic Paints\u00a0S-549334",
        "url": "https://www.tinydeal.com/liquid-luminous-coating-fluorescent-bodyface-paint-luminous-acrylic-paints-p-175143.html",
        "discounted_price": "$2.22",
        "original_price": "$4.00 "
    },
    {
        "title": "IP67 P8 Smart Watch Wristband Men Women Monitor Smartwatch Tracker For Phone\u00a0E-580457",
        "url": "https://www.tinydeal.com/ip67-p8-smart-watch-wristband-men-women-monitor-smartwatch-tracker-for-phone-p-200649.html",
        "discounted_price": "$18.73",
        "original_price": "$36.77 "
    },
    {
        "title": "X96Q Android 10.0 TV Box Quad Core Allwinner H313 4K TV Box 1GB RAM 8GB ROM\u00a0E-581779",
        "url": "https://www.tinydeal.com/x96q-android-100-tv-box-quad-core-allwinner-h313-4k-tv-box-1gb-ram-8gb-rom-p-201108.html",
        "discounted_price": "$28.35",
        "original_price": "$39.69 "
    },
    {
        "title": "1 Pair of Silicone Magnetic Losing Weight Toe Rings\u00a0HBI-13397",
        "url": "https://www.tinydeal.com/1-pair-of-silicone-magnetic-losing-weight-toe-rings-p-12727.html",
        "discounted_price": "$1.07",
        "original_price": "$3.26 "
    },
    {
        "title": "NAVIFORCE NF9161 Men's Watches Top Luxury Brand Analog Stainless Steel\u00a0WWT-580848",
        "url": "https://www.tinydeal.com/naviforce-nf9161-mens-watches-top-luxury-brand-analog-stainless-steel-p-200814.html",
        "discounted_price": "$18.79",
        "original_price": "$33.83 "
    },
    {
        "title": "Neoprene Short Beach Socks Diving Socks Non-Slip Antiskid Scuba Dive Boots\u00a0SGD-548443",
        "url": "https://www.tinydeal.com/neoprene-short-beach-socks-diving-socks-non-slip-antiskid-scuba-dive-boots-p-174657.html",
        "discounted_price": "$3.41",
        "original_price": "$3.80 "
    },
    {
        "title": "Women Arm Shaper Back Shoulder Corrector Humpback Posture Corrector\u00a0DUW-584071",
        "url": "https://www.tinydeal.com/women-arm-shaper-back-shoulder-corrector-humpback-posture-corrector-p-201650.html",
        "discounted_price": "$10.65",
        "original_price": "$19.69 "
    },
    {
        "title": "10 pcs Snore Stopper Silicone Nose Clip Sleeping Device Nasal Dilators\u00a0KB-531795",
        "url": "https://www.tinydeal.com/10-pcs-snore-stopper-silicone-nose-clip-sleeping-device-nasal-dilators-p-166469.html",
        "discounted_price": "$5.89",
        "original_price": "$10.59 "
    },
    {
        "title": "Hair Cutting Cloak Gown Umbrella Hair Salon Cape Hairdresser Haircut Bib Apron\u00a0HKI-549496",
        "url": "https://www.tinydeal.com/hair-cutting-cloak-gown-umbrella-hair-salon-cape-hairdresser-haircut-bib-apron-p-175156.html",
        "discounted_price": "$3.71",
        "original_price": "$6.87 "
    },
    {
        "title": "Baellerry Mini Pop Up Rfid Wallet Men Slim PU Leather Business Credit Card\u00a0RTH-577197",
        "url": "https://www.tinydeal.com/baellerry-mini-pop-up-rfid-wallet-men-slim-pu-leather-business-credit-card-p-201336.html",
        "discounted_price": "$6.95",
        "original_price": "$8.68 "
    },
    {
        "title": "Wireless Mouse Vertical Mouse Ergonomic Optical 2400 DPI 6 Buttons Mause\u00a0ECAMS-582851",
        "url": "https://www.tinydeal.com/wireless-mouse-vertical-mouse-ergonomic-optical-2400-dpi-6-buttons-mause-p-200748.html",
        "discounted_price": "$12.57",
        "original_price": "$22.62 "
    },
    {
        "title": "SOKI Sport Watches Leather Strap Quartz Casual Business Male Wristwatches\u00a0WWT-580302",
        "url": "https://www.tinydeal.com/soki-sport-watches-leather-strap-quartz-casual-business-male-wristwatches-p-201543.html",
        "discounted_price": "$3.90",
        "original_price": "$7.41 "
    }
][
{"title": "TWS F9 Bluetooth Earphone Touch Wireless Headphones 8D Stereo Sports Earbuds EEP-582910", "url": "https://www.tinydeal.com/tws-f9-bluetooth-earphone-touch-wireless-headphones-8d-stereo-sports-earbuds-p-200780.html", "discounted_price": "$12.07", "original_price": "$24.02 "},
{"title": "Transparent Anti Droplet Dust-proof Medical Face Shield Face Cover Mask HHI-581539", "url": "https://www.tinydeal.com/transparent-anti-droplet-dust-proof-medical-face-shield-face-cover-mask-p-200336.html", "discounted_price": "$2.82", "original_price": "$3.48 "},
{"title": "Fsat Quick Charge 3.0 4.0 QC3.0 Fast Charging Tablet Wall Adapter HHITH-582324", "url": "https://www.tinydeal.com/fsat-quick-charge-30-40-qc30-fast-charging-tablet-wall-adapter-p-201049.html", "discounted_price": "$3.75", "original_price": "$6.74 "},
{"title": "10 x Transparent Anti Droplet Dust-proof Medical Face Shield Face Cover Mask KB-581546", "url": "https://www.tinydeal.com/10-x-transparent-anti-droplet-dust-proof-medical-face-shield-face-cover-mask-p-200338.html", "discounted_price": "$13.83", "original_price": "$24.61 "},
{"title": "Micro SD TF Card 32GB Class Flash Memory Card for Smartphone Adapter EFM-582223", "url": "https://www.tinydeal.com/micro-sd-tf-card-32gb-class-flash-memory-card-for-smartphone-adapter-p-201054.html", "discounted_price": "$4.77", "original_price": "$8.59 "},
{"title": "Mini Airtight Sealer Machine for Plastic Bag - Assorted Color HLI-48626", "url": "https://www.tinydeal.com/mini-airtight-sealer-machine-for-plastic-bag-assorted-color-p-39392.html", "discounted_price": "$2.52", "original_price": "$5.86 "},
{"title": "100 LED Solar Light  Solar Lamp Powered Sunlight 3 Modes PIR Motion Sensor RTH-577401", "url": "https://www.tinydeal.com/100-led-solar-light-solar-lamp-powered-sunlight-3-modes-pir-motion-sensor-p-201640.html", "discounted_price": "$9.02", "original_price": "$14.89 "},
{"title": "Wireless Headphones Bluetooth 5.0 Foldable Stereo Adjustable Earphones RTH-578691", "url": "https://www.tinydeal.com/wireless-headphones-bluetooth-50-foldable-stereo-adjustable-earphones-p-201646.html", "discounted_price": "$15.00", "original_price": "$21.75 "},
{"title": "0.25W Intelligent Cabinet Sensor Lights HHI-546845", "url": "https://www.tinydeal.com/025w-intelligent-cabinet-sensor-lights-p-174242.html", "discounted_price": "$1.96", "original_price": "$5.28 "},
{"title": "Fully USB Charging Automatic Foam Soap Dispenser Deep Cleaning HHI-581206", "url": "https://www.tinydeal.com/fully-usb-charging-automatic-foam-soap-dispenser-deep-cleaning-p-201087.html", "discounted_price": "$19.11", "original_price": "$22.93 "},
{"title": "X96Q Android 10.0 TV Box Quad Core Allwinner H313 4K TV Box 2GB RAM 16GB ROM E-581778", "url": "https://www.tinydeal.com/x96q-android-100-tv-box-quad-core-allwinner-h313-4k-tv-box-2gb-ram-16gb-rom-p-201107.html", "discounted_price": "$31.15", "original_price": "$43.61 "},
{"title": "Air Circulation Fan Mute Desktop Fans Atmosphere Ventilation Electric Fan HHI-581327", "url": "https://www.tinydeal.com/air-circulation-fan-mute-desktop-fans-atmosphere-ventilation-electric-fan-p-200717.html", "discounted_price": "$19.21", "original_price": "$34.58 "},
{"title": "Silicone Nipple Cover Stickers Adhesive Bra Reusable Invisible Nipple Cover HHI-550767", "url": "https://www.tinydeal.com/silicone-nipple-cover-stickers-adhesive-bra-reusable-invisible-nipple-cover-p-175493.html", "discounted_price": "$2.00", "original_price": "$2.40 "},
{"title": "Autumn Winter Leather Baseball Cap Men Women Gorras Planas Snapback Hat RTH-576721", "url": "https://www.tinydeal.com/autumn-winter-leather-baseball-cap-men-women-gorras-planas-snapback-hat-p-201587.html", "discounted_price": "$8.54", "original_price": "$10.67 "},
{"title": "Wireless Earphones TWS Wireless Bluetooth 5.0 LED Display Waterproof Headphone EEP-580809", "url": "https://www.tinydeal.com/wireless-earphones-tws-wireless-bluetooth-50-led-display-waterproof-headphone-p-201417.html", "discounted_price": "$16.00", "original_price": "$17.59 "},
{"title": "3 in 1 Cable Nylon-Coating Fast Charging 8Pin Type-C Micro-USB EPA-530685", "url": "https://www.tinydeal.com/3-in-1-cable-nylon-coating-fast-charging-8pin-type-micro-usb-p-165980.html", "discounted_price": "$2.53", "original_price": "$4.37 "},
{"title": "Xiaomi Turok Steinhardt TS Brand Polarized Stainless Mirror Lenses Sunglasses S-582106", "url": "https://www.tinydeal.com/xiaomi-turok-steinhardt-ts-brand-polarized-stainless-mirror-lenses-sunglasses-p-200936.html", "discounted_price": "$20.22", "original_price": "$34.38 "},
{"title": "K08 Wireless Headphone Bluetooth5.0 Bone Conduction Headsets Wireless EEP-583532", "url": "https://www.tinydeal.com/k08-wireless-headphone-bluetooth50-bone-conduction-headsets-wireless-p-201440.html", "discounted_price": "$12.33", "original_price": "$22.81 "},
{"title": "Compression Socks for Man Woman STH-563907", "url": "https://www.tinydeal.com/compression-socks-for-man-woman-p-180225.html", "discounted_price": "$2.43", "original_price": "$6.45 "},
{"title": "GM320 Infrared Thermometer Non-Contact Laser Gun IR Thermometer EDT-528767", "url": "https://www.tinydeal.com/gm320-infrared-thermometer-non-contact-laser-gun-ir-thermometer-p-165306.html", "discounted_price": "$16.97", "original_price": "$18.94 "},
{"title": "F9 TWS Wireless Earphones Bluetooth 5.0 F9 TWS Bluetooth headphone EEP-583405", "url": "https://www.tinydeal.com/f9-tws-wireless-earphones-bluetooth-50-f9-tws-bluetooth-headphone-p-201446.html", "discounted_price": "$12.13", "original_price": "$21.84 "},
{"title": "Genuine Leather Man Messenger Bags Vintage Cow Leather Small Shoulder Bag DBA-584138", "url": "https://www.tinydeal.com/genuine-leather-man-messenger-bags-vintage-cow-leather-small-shoulder-bag-p-202214.html", "discounted_price": "$24.87", "original_price": "$44.76 "},
{"title": "Kangaroo Brand Leather Messenger Bag Man Handbag Chest Bag RTH-577738", "url": "https://www.tinydeal.com/kangaroo-brand-leather-messenger-bag-man-handbag-chest-bag-p-200744.html", "discounted_price": "$17.82", "original_price": "$21.38 "},
{"title": "100LED Solar Light Outdoor Solar Lamp PIR Motion Sensor Wall Light Waterproof HHIHE-582872", "url": "https://www.tinydeal.com/100led-solar-light-outdoor-solar-lamp-pir-motion-sensor-wall-light-waterproof-p-201245.html", "discounted_price": "$7.49", "original_price": "$10.12 "},
{"title": "70mai Smart Dash Cam Pro English Voice Car DVR Camera GPS Auto Night Vision RCM-581275", "url": "https://www.tinydeal.com/70mai-smart-dash-cam-pro-english-voice-car-dvr-camera-gps-auto-night-vision-p-201053.html", "discounted_price": "$90.09", "original_price": "$108.11 "},
{"title": "Outdoor Lights Solar Powered LED Wall Lamp Porch Lights Sensor Motion Sensor HSI-582757", "url": "https://www.tinydeal.com/outdoor-lights-solar-powered-led-wall-lamp-porch-lights-sensor-motion-sensor-p-201016.html", "discounted_price": "$8.17", "original_price": "$14.70 "},
{"title": "Smart Wireless Bluetooth Stereo Headset Headphone with MIC RTH-576453", "url": "https://www.tinydeal.com/smart-wireless-bluetooth-stereo-headset-headphone-with-mic-p-201645.html", "discounted_price": "$15.69", "original_price": "$25.11 "},
{"title": "Silicone Stretch Lids Food Saver Covers Set – 6pcs HKI-550666", "url": "https://www.tinydeal.com/silicone-stretch-lids-food-saver-covers-set-–-6pcs-p-175450.html", "discounted_price": "$5.28", "original_price": "$6.87 "},
{"title": "Men Genuine Leather Strap Male Belts for New Classic Vintage Pin Buckle Strap HHI-578703", "url": "https://www.tinydeal.com/men-genuine-leather-strap-male-belts-for-new-classic-vintage-pin-buckle-strap-p-201601.html", "discounted_price": "$8.18", "original_price": "$15.13 "},
{"title": "Personal Portable Photography Studio LED Light Room Light Weight EVA-538137", "url": "https://www.tinydeal.com/personal-portable-photography-studio-led-light-room-light-weight-p-170497.html", "discounted_price": "$10.62", "original_price": "$18.48 "},
{"title": "DUBERY Polarized Sunglasses Men's Driving Shades Male Sun Glasses S-580864", "url": "https://www.tinydeal.com/dubery-polarized-sunglasses-mens-driving-shades-male-sun-glasses-p-200630.html", "discounted_price": "$5.89", "original_price": "$15.20 "},
{"title": "E1 Bone Conduction Headphones Bluetooth 4.1 Wireless Bass HiFi Headsets EEP-545247", "url": "https://www.tinydeal.com/e1-bone-conduction-headphones-bluetooth-41-wireless-bass-hifi-headsets-p-173784.html", "discounted_price": "$11.12", "original_price": "$74.68 "},
{"title": "DUBERY Vintage Sunglasses Polarized Men's Sun Glasses For Men S-580871", "url": "https://www.tinydeal.com/dubery-vintage-sunglasses-polarized-mens-sun-glasses-for-men-p-200631.html", "discounted_price": "$6.32", "original_price": "$8.22 "},
{"title": "GM321 Non-contact Infrared Thermometer -50° to 380° EDT-568819", "url": "https://www.tinydeal.com/gm321-non-contact-infrared-thermometer-50°-to-380°-p-181807.html", "discounted_price": "$24.87", "original_price": "$29.84 "},
{"title": "Xiaomi ENCHEN Sharp3S Men's Electric Hair Clipper USB Rechargeable Hair Trimmer HHIHE-581692", "url": "https://www.tinydeal.com/xiaomi-enchen-sharp3s-mens-electric-hair-clipper-usb-rechargeable-hair-trimmer-p-201119.html", "discounted_price": "$18.40", "original_price": "$27.59 "},
{"title": "Xiaomi 3D Men Electric Shaver Razor Enchen BlackStone3 IPX7 Waterproof HHI-580937", "url": "https://www.tinydeal.com/xiaomi-3d-men-electric-shaver-razor-enchen-blackstone3-ipx7-waterproof-p-200797.html", "discounted_price": "$24.27", "original_price": "$29.13 "},
{"title": "XIAOMI MIJIA VIOMI Blender Electric Kitchen Mixer Juicer Fruit Cup Quick Juicing HHI-581813", "url": "https://www.tinydeal.com/xiaomi-mijia-viomi-blender-electric-kitchen-mixer-juicer-fruit-cup-quick-juicing-p-201105.html", "discounted_price": "$33.74", "original_price": "$40.49 "},
{"title": "S03 Smart Watch Waterproof Activity Tracker Smart Band Bracelet E-582866", "url": "https://www.tinydeal.com/s03-smart-watch-waterproof-activity-tracker-smart-band-bracelet-p-200781.html", "discounted_price": "$11.95", "original_price": "$24.02 "},
{"title": "2PCS Automobile Electrostatic Sunshade Car Sunscreen Sticker RTH-391611", "url": "https://www.tinydeal.com/2pcs-automobile-electrostatic-sunshade-car-sunscreen-sticker--p-148929.html", "discounted_price": "$4.23", "original_price": "$7.79 "},
{"title": "1/2/4 Pair Magnetic Therapy Thermal Self-Heating Knee Pad Belt BBI-276865", "url": "https://www.tinydeal.com/124-pair-magnetic-therapy-thermal-self-heating-knee-pad-belt-p-118227.html", "discounted_price": "$3.64", "original_price": "$4.74 "},
{"title": "M108 Smart Wireless WiFi HD Visual Doorbell IP Door Bell Infrared Night Vision HHIHE-580663", "url": "https://www.tinydeal.com/m108-smart-wireless-wifi-hd-visual-doorbell-ip-door-bell-infrared-night-vision--p-201397.html", "discounted_price": "$37.58", "original_price": "$60.12 "},
{"title": "Camping Sleeping Pad Ultralight Waterproof self Inflating Sleeping Hiking HHI-582472", "url": "https://www.tinydeal.com/camping-sleeping-pad-ultralight-waterproof-self-inflating-sleeping-hiking-p-200843.html", "discounted_price": "$30.96", "original_price": "$40.25 "},
{"title": "Men Electric Shaver Razor Beard Hair Clipper Trimmer Grooming Rechargeable Hair HHI-580827", "url": "https://www.tinydeal.com/men-electric-shaver-razor-beard-hair-clipper-trimmer-grooming-rechargeable-hair-p-201462.html", "discounted_price": "$24.27", "original_price": "$35.19 "},
{"title": "Outdoor USB Rechargeable Personal Alarm Emergency Security Alarm Keychain S-583319", "url": "https://www.tinydeal.com/outdoor-usb-rechargeable-personal-alarm-emergency-security-alarm-keychain-p-200941.html", "discounted_price": "$5.93", "original_price": "$8.89 "},
{"title": "Liquid Luminous Coating Fluorescent Body/Face Paint Luminous Acrylic Paints S-549334", "url": "https://www.tinydeal.com/liquid-luminous-coating-fluorescent-bodyface-paint-luminous-acrylic-paints-p-175143.html", "discounted_price": "$2.22", "original_price": "$4.00 "},
{"title": "IP67 P8 Smart Watch Wristband Men Women Monitor Smartwatch Tracker For Phone E-580457", "url": "https://www.tinydeal.com/ip67-p8-smart-watch-wristband-men-women-monitor-smartwatch-tracker-for-phone-p-200649.html", "discounted_price": "$18.73", "original_price": "$36.77 "},
{"title": "X96Q Android 10.0 TV Box Quad Core Allwinner H313 4K TV Box 1GB RAM 8GB ROM E-581779", "url": "https://www.tinydeal.com/x96q-android-100-tv-box-quad-core-allwinner-h313-4k-tv-box-1gb-ram-8gb-rom-p-201108.html", "discounted_price": "$28.35", "original_price": "$39.69 "},
{"title": "1 Pair of Silicone Magnetic Losing Weight Toe Rings HBI-13397", "url": "https://www.tinydeal.com/1-pair-of-silicone-magnetic-losing-weight-toe-rings-p-12727.html", "discounted_price": "$1.07", "original_price": "$3.26 "},
{"title": "NAVIFORCE NF9161 Men's Watches Top Luxury Brand Analog Stainless Steel WWT-580848", "url": "https://www.tinydeal.com/naviforce-nf9161-mens-watches-top-luxury-brand-analog-stainless-steel-p-200814.html", "discounted_price": "$18.79", "original_price": "$33.83 "},
{"title": "Neoprene Short Beach Socks Diving Socks Non-Slip Antiskid Scuba Dive Boots SGD-548443", "url": "https://www.tinydeal.com/neoprene-short-beach-socks-diving-socks-non-slip-antiskid-scuba-dive-boots-p-174657.html", "discounted_price": "$3.41", "original_price": "$3.80 "},
{"title": "Women Arm Shaper Back Shoulder Corrector Humpback Posture Corrector DUW-584071", "url": "https://www.tinydeal.com/women-arm-shaper-back-shoulder-corrector-humpback-posture-corrector-p-201650.html", "discounted_price": "$10.65", "original_price": "$19.69 "},
{"title": "10 pcs Snore Stopper Silicone Nose Clip Sleeping Device Nasal Dilators KB-531795", "url": "https://www.tinydeal.com/10-pcs-snore-stopper-silicone-nose-clip-sleeping-device-nasal-dilators-p-166469.html", "discounted_price": "$5.89", "original_price": "$10.59 "},
{"title": "Hair Cutting Cloak Gown Umbrella Hair Salon Cape Hairdresser Haircut Bib Apron HKI-549496", "url": "https://www.tinydeal.com/hair-cutting-cloak-gown-umbrella-hair-salon-cape-hairdresser-haircut-bib-apron-p-175156.html", "discounted_price": "$3.71", "original_price": "$6.87 "},
{"title": "Baellerry Mini Pop Up Rfid Wallet Men Slim PU Leather Business Credit Card RTH-577197", "url": "https://www.tinydeal.com/baellerry-mini-pop-up-rfid-wallet-men-slim-pu-leather-business-credit-card-p-201336.html", "discounted_price": "$6.95", "original_price": "$8.68 "},
{"title": "Wireless Mouse Vertical Mouse Ergonomic Optical 2400 DPI 6 Buttons Mause ECAMS-582851", "url": "https://www.tinydeal.com/wireless-mouse-vertical-mouse-ergonomic-optical-2400-dpi-6-buttons-mause-p-200748.html", "discounted_price": "$12.57", "original_price": "$22.62 "},
{"title": "SOKI Sport Watches Leather Strap Quartz Casual Business Male Wristwatches WWT-580302", "url": "https://www.tinydeal.com/soki-sport-watches-leather-strap-quartz-casual-business-male-wristwatches-p-201543.html", "discounted_price": "$3.90", "original_price": "$7.41 "}
]